deplacy/__init__.py
deplacy/conllusvgRtoL.js
deplacy/conllusvgedit.js
deplacy/conllusvgview.js
deplacy/deplacy.py
deplacy/deprelja.py
deplacy/editor.html
deplacy/editorRtoL.html
deplacy/header.html
deplacy/headerRtoL.html
deplacy/tailer.html
deplacy-2.1.1.dist-info/LICENSE.txt
deplacy-2.1.1.dist-info/METADATA
deplacy-2.1.1.dist-info/WHEEL
deplacy-2.1.1.dist-info/top_level.txt
deplacy-2.1.1.dist-info/RECORD
