Metadata-Version: 2.1
Name: deplacy
Version: 2.1.1
Summary: CUI-based Tree Visualizer for Universal Dependencies and Immediate Catena Analysis
Home-page: https://github.com/KoichiYasuoka/deplacy
Author: Koichi Yasuoka
Author-email: yasuoka@kanji.zinbun.kyoto-u.ac.jp
License: MIT
Project-URL: Source, https://github.com/KoichiYasuoka/deplacy
Project-URL: Tracker, https://github.com/KoichiYasuoka/deplacy/issues
Keywords: spacy stanza nlp
Classifier: License :: OSI Approved :: MIT License
Classifier: Programming Language :: Python :: 3
Classifier: Operating System :: OS Independent
Classifier: Topic :: Text Processing :: Linguistic
Requires-Python: >=3.6
License-File: LICENSE.txt
